discord_chatbot/__init__.py
discord_chatbot/_resources.py
discord_chatbot/config.py
discord_chatbot/discord_bot.py
discord_chatbot/handlers.py
discord_chatbot/keyboards.py
discord_chatbot/main.py
discord_chatbot/requesters.py
discord_chatbot/runner.py
discord_chatbot/states.py
discord_chatbot/utils.py
discord_chatbot/vocabulary.py
discord_chatbot_deskent-1.3.6.dist-info/LICENSE
discord_chatbot_deskent-1.3.6.dist-info/METADATA
discord_chatbot_deskent-1.3.6.dist-info/WHEEL
discord_chatbot_deskent-1.3.6.dist-info/top_level.txt
discord_chatbot_deskent-1.3.6.dist-info/RECORD
