Metadata-Version: 2.1
Name: discord-chatbot-deskent
Version: 1.3.6
Summary: Discord chat bot
Author: Deskent
Author-email: battenetciz@gmail.com
Classifier: License :: OSI Approved :: MIT License
Classifier: Programming Language :: Python
Classifier: Programming Language :: Python :: 3
Classifier: Operating System :: OS Independent
Requires-Python: >=3.7
License-File: LICENSE
Requires-Dist: aiogram (==2.18)
Requires-Dist: pydantic (==1.9.1)
Requires-Dist: python-dotenv (==0.19.2)
Requires-Dist: myloguru-deskent (==0.0.12)
